MANIFEST.in
requirements.txt
setup.cfg
setup.py
xbee_helper/__init__.py
xbee_helper/const.py
xbee_helper/device.py
xbee_helper/exceptions.py
xbee_helper.egg-info/PKG-INFO
xbee_helper.egg-info/SOURCES.txt
xbee_helper.egg-info/dependency_links.txt
xbee_helper.egg-info/not-zip-safe
xbee_helper.egg-info/requires.txt
xbee_helper.egg-info/top_level.txt