Metadata-Version: 1.1
Name: xbee-helper
Version: 0.0.5
Summary: This project offers a high level API to an XBee device running an up-
Home-page: https://github.com/flyte/xbee-helper
Author: Ellis Percival
Author-email: xbee-helper@failcode.co.uk
License: MIT
Platform: UNKNOWN
Classifier: Programming Language :: Python
Classifier: Intended Audience :: Developers
Classifier: License :: OSI Approved :: MIT License
Classifier: Natural Language :: English
Classifier: Operating System :: OS Independent
Classifier: Topic :: Communications
Classifier: Topic :: Home Automation
Classifier: Topic :: Software Development :: Embedded Systems
Classifier: Topic :: System :: Networking
